app_common/__init__.py
app_common/api_gateway_utils.py
app_common/app_common_stack.py
app_common/app_config.py
app_common/app_utils.py
app_common/base_lambda_handler.py
app_common/dynamodb_utils.py
app_common/exceptions_utils.py
app_common/utils4tests.py
app_scripts/__init__.py
app_scripts/app_deploy.py
app_scripts/app_install_reqs.py
app_scripts/app_reset_venv.py
app_scripts/app_setup.py
app_scripts/app_setup_execution.py
app_scripts/app_test.py
aws_cdk_common-0.1.58.dist-info/METADATA
aws_cdk_common-0.1.58.dist-info/WHEEL
aws_cdk_common-0.1.58.dist-info/RECORD
