Metadata-Version: 2.3
Name: aws-cdk-common
Version: 0.1.58
Summary: A shared package for common modules and constants for AWS Lambda applications
License: MIT
Author: LARS AI
Requires-Python: >=3.11,<4.0
Classifier: License :: OSI Approved :: MIT License
Classifier: Programming Language :: Python :: 3
Classifier: Programming Language :: Python :: 3.11
Classifier: Programming Language :: Python :: 3.12
Classifier: Programming Language :: Python :: 3.13
